<experiment version="12.4">
<collector>Studio 12.6 Performance Analyzer 12.6 Linux_x64 2017/05/24</collector>
</experiment>
<system hostname="n-62-21-37" arch="x86_64" os="Linux 3.10.0-1062.7.1.el7.x86_64" pagesz="4096" npages="65891578">
  <cpu id="0" clk="2200"/>
  <cpu id="1" clk="1199"/>
  <cpu id="2" clk="1245"/>
  <cpu id="3" clk="1291"/>
  <cpu id="4" clk="1200"/>
  <cpu id="5" clk="1199"/>
  <cpu id="6" clk="1199"/>
  <cpu id="7" clk="1299"/>
  <cpu id="8" clk="1199"/>
  <cpu id="9" clk="1397"/>
  <cpu id="10" clk="1199"/>
  <cpu id="11" clk="1199"/>
  <cpu id="12" clk="1204"/>
  <cpu id="13" clk="1199"/>
  <cpu id="14" clk="1199"/>
  <cpu id="15" clk="1199"/>
  <cpu id="16" clk="1191"/>
  <cpu id="17" clk="1203"/>
  <cpu id="18" clk="1191"/>
  <cpu id="19" clk="1193"/>
  <cpu id="20" clk="1204"/>
  <cpu id="21" clk="1201"/>
  <cpu id="22" clk="1199"/>
  <cpu id="23" clk="1391"/>
</system>
<process pid="28098"></process>
<process ppid="27969"></process>
<process pgrp="27964"></process>
<process sid="7875"></process>
<process cwd="/zhome/e3/7/118026/Desktop/gits/HPC"></process>
<process wsize="64"></process>
<process stackbase="0x7ffd0d3979b0"></process>
<process>./matmult_c.gcc blk 2000 2000 2000 64</process>
<profile name="profile" ptimer="10007" numstates="1">
  <profdata fname="profile"/>
  <profpckt kind="8" uname="Clock profiling data">
    <field name="LWPID" uname="Lightweight process id" offset="8" type="INT64"/>
    <field name="THRID" uname="Thread number" offset="16" type="INT64"/>
    <field name="CPUID" uname="CPU id" offset="24" type="INT32"/>
    <field name="TSTAMP" uname="High resolution timestamp" offset="32" type="INT64"/>
    <field name="FRINFO" offset="40" type="INT64"/>
    <field name="MSTATE" uname="Thread state" offset="48" type="INT32"/>
    <field name="NTICK" uname="Duration" offset="52" type="INT32"/>
  </profpckt>
</profile>
<profdata fname="hwcounters"/>
<profpckt kind="3" uname="Hardware counter profiling data">
    <field name="LWPID" uname="Lightweight process id" offset="8" type="INT64"/>
    <field name="THRID" uname="Thread number" offset="16" type="INT64"/>
    <field name="CPUID" uname="CPU id" offset="24" type="INT32"/>
    <field name="TSTAMP" uname="High resolution timestamp" offset="32" type="INT64"/>
    <field name="FRINFO" offset="40" type="INT64"/>
    <field name="HWCTAG" uname="Hardware counter index" offset="48" type="INT32"/>
    <field name="HWCINT" uname="Hardware counter interval" offset="56" type="INT64"/>
</profpckt>
<profile name="hwcounter" cpuver="2070" hwcname="dch" int_name="mem_load_uops_retired.l1_hit" interval="10010001" tag="0" memop="0"/>
<profile name="hwcounter" cpuver="2070" hwcname="dcm" int_name="mem_load_uops_retired.l1_miss" interval="3201001" tag="1" memop="0"/>
<profile name="hwcounter" cpuver="2070" hwcname="l2h" int_name="mem_load_uops_retired.l2_hit" interval="3201001" tag="2" memop="0"/>
<profile name="hwcounter" cpuver="2070" hwcname="l2m" int_name="mem_load_uops_retired.l2_miss" interval="1001001" tag="3" memop="0"/>
<dataptr name="frameinfo" format="binary"/>
<setting sample_period="1"/>
<setting linetrace="fork|exec|combo"/>
<setting collenv="SP_COLLECTOR_FOUNDER=0"/>
<setting collenv="SP_COLLECTOR_ORIGIN_COLLECT=1"/>
<event kind="run" tstamp="2763536.977887904" time="1578489058" tm_zone="-3600"/>
<event kind="sample" tstamp="0.000062630" id="0" label="collector_open_experiment"/>
<event kind="sample" tstamp="1.008362220" id="1" label="periodic"/>
<event kind="sample" tstamp="2.002351351" id="2" label="periodic"/>
<event kind="sample" tstamp="3.005342227" id="3" label="periodic"/>
<event kind="sample" tstamp="4.009332526" id="4" label="periodic"/>
<event kind="sample" tstamp="5.002322160" id="5" label="periodic"/>
<event kind="sample" tstamp="6.005312228" id="6" label="periodic"/>
<event kind="sample" tstamp="7.009303276" id="7" label="periodic"/>
<event kind="sample" tstamp="8.002292965" id="8" label="periodic"/>
<event kind="sample" tstamp="9.008282985" id="9" label="periodic"/>
<event kind="sample" tstamp="10.001273442" id="10" label="periodic"/>
<event kind="sample" tstamp="11.004264853" id="11" label="periodic"/>
<event kind="sample" tstamp="12.001254037" id="12" label="periodic"/>
<event kind="sample" tstamp="13.003244407" id="13" label="periodic"/>
<event kind="sample" tstamp="14.007234206" id="14" label="periodic"/>
<event kind="sample" tstamp="15.000225459" id="15" label="periodic"/>
<event kind="sample" tstamp="16.003215600" id="16" label="periodic"/>
<event kind="sample" tstamp="17.007207602" id="17" label="periodic"/>
<event kind="sample" tstamp="18.003198013" id="18" label="periodic"/>
<event kind="sample" tstamp="19.005187980" id="19" label="periodic"/>
<event kind="sample" tstamp="20.009176857" id="20" label="periodic"/>
<event kind="sample" tstamp="21.003166608" id="21" label="periodic"/>
<event kind="sample" tstamp="22.005156403" id="22" label="periodic"/>
<event kind="sample" tstamp="23.009146536" id="23" label="periodic"/>
<event kind="sample" tstamp="24.006137138" id="24" label="periodic"/>
<event kind="sample" tstamp="25.008127568" id="25" label="periodic"/>
<event kind="sample" tstamp="26.005118286" id="26" label="periodic"/>
<event kind="sample" tstamp="27.007107555" id="27" label="periodic"/>
<event kind="sample" tstamp="28.000099554" id="28" label="periodic"/>
<event kind="sample" tstamp="29.003088271" id="29" label="periodic"/>
<event kind="sample" tstamp="30.007078354" id="30" label="periodic"/>
<event kind="sample" tstamp="31.000068978" id="31" label="periodic"/>
<event kind="sample" tstamp="32.003058977" id="32" label="periodic"/>
<event kind="sample" tstamp="33.007049515" id="33" label="periodic"/>
<event kind="sample" tstamp="34.001039465" id="34" label="periodic"/>
<event kind="sample" tstamp="35.008031605" id="35" label="periodic"/>
<event kind="sample" tstamp="36.003020961" id="36" label="periodic"/>
<event kind="sample" tstamp="37.008011644" id="37" label="periodic"/>
<event kind="sample" tstamp="38.001001126" id="38" label="periodic"/>
<event kind="sample" tstamp="39.003992755" id="39" label="periodic"/>
<event kind="sample" tstamp="40.007982388" id="40" label="periodic"/>
<event kind="sample" tstamp="41.001971215" id="41" label="periodic"/>
<event kind="sample" tstamp="42.003961641" id="42" label="periodic"/>
<event kind="sample" tstamp="43.000952169" id="43" label="periodic"/>
<event kind="sample" tstamp="44.002942114" id="44" label="periodic"/>
<event kind="sample" tstamp="45.006933079" id="45" label="periodic"/>
<event kind="sample" tstamp="46.009923859" id="46" label="periodic"/>
<event kind="sample" tstamp="47.003913047" id="47" label="periodic"/>
<event kind="sample" tstamp="48.009903705" id="48" label="periodic"/>
<event kind="sample" tstamp="49.002893663" id="49" label="periodic"/>
<event kind="sample" tstamp="50.006884498" id="50" label="periodic"/>
<event kind="sample" tstamp="51.009874600" id="51" label="periodic"/>
<event kind="sample" tstamp="52.006864886" id="52" label="periodic"/>
<event kind="sample" tstamp="53.008854985" id="53" label="periodic"/>
<event kind="sample" tstamp="54.002845610" id="54" label="periodic"/>
<event kind="sample" tstamp="55.004835392" id="55" label="periodic"/>
<event kind="sample" tstamp="56.008825359" id="56" label="periodic"/>
<event kind="sample" tstamp="57.003816145" id="57" label="periodic"/>
<event kind="sample" tstamp="58.005806357" id="58" label="periodic"/>
<event kind="sample" tstamp="59.001796671" id="59" label="periodic"/>
<event kind="sample" tstamp="60.004786957" id="60" label="periodic"/>
<event kind="sample" tstamp="61.000777042" id="61" label="periodic"/>
<event kind="sample" tstamp="62.002767146" id="62" label="periodic"/>
<event kind="sample" tstamp="63.006756974" id="63" label="periodic"/>
<event kind="sample" tstamp="64.000747345" id="64" label="periodic"/>
<event kind="sample" tstamp="65.002737448" id="65" label="periodic"/>
<event kind="sample" tstamp="66.006728476" id="66" label="periodic"/>
<event kind="sample" tstamp="67.000718502" id="67" label="periodic"/>
<event kind="sample" tstamp="68.002709574" id="68" label="periodic"/>
<event kind="sample" tstamp="69.009698733" id="69" label="periodic"/>
<event kind="sample" tstamp="70.002689415" id="70" label="periodic"/>
<event kind="sample" tstamp="71.009678879" id="71" label="periodic"/>
<event kind="sample" tstamp="71.359619019" id="72" label="collector_close_experiment"/>
<event kind="run" tstamp="2763536.977887904" time="1578489058" tm_zone="-3600"/>
<event kind="exit" tstamp="71.359052949"/>
<event kind="comment" id="400">Archive command ` /opt/oracle/developerstudio12.6/bin/../bin/er_archive -n -O /zhome/e3/7/118026/Desktop/gits/HPC/6_consoles.5029777.er/er_archive.log /zhome/e3/7/118026/Desktop/gits/HPC/6_consoles.5029777.er'</event>
                                                                                                                                                                                                                                                                                                                                                                                                                                                                                                                                                                                                                                                                                                                                                                                                                                                                                                                                                                                                                                                                                                                                                                                                                                                                                                                                                                                                                                                                                                                                                                                                                                                                                                                                                                                                                                                                                                                                                                                                                                                                                                                                                                                                                                                                                                                                                                                                                                                                                                                                                                                                                                                                                                                                                                                                                                                                                                                                                                                                                                                                                                                                                                                                                                                                                                                                                                                                                                                                                                                                                                                                                                                                                                                                                                                                                                                                                                                                                                                                                                                                                                                                                                                                                                                                                                                                                                                                                                                                                                                                                                                                                                                                                                                                                                                                                                                                                                                                                                                                                                                                                                                                                                                                                                                                                                                                                                                                                                                                                                                                                                                                                                                                                                                                                                                                                                                                                                                                                                                                                                                                                                                                                                                                                                                                                                                                                                                                                                                                                                                                                                                                                                                                                                                                                                                                                                                                                                                                                                                                                                                                                                                                                                                                                                                                                                                                                                                                                                                                                                                                                                                                                                                                                                                                                                                                                                                                                                                                                                                                                                                                                                                                                                                                                                                                                                                                                                                                                                                                                                                                                                                                                                                                                                                                                                                                                                                                                                                                                                                                                                                                                                                                                                                                                                                                                                                                                                                                                                                                                                                                                                                                                                                                                                                                                                                                                                                                                                                                                                                                                                                                                                                                                                                                                                                                                                                                                                                                                                                                                                                                                                                                                                                                                                                                                                                                                                                                                                                                                                                                                                                                                                                                                                                                                                                                                                                                                                                                                                                                                                                                                                                                                                                                                                                                                                                                                                                                                                                                                                                                                                                                                                                                                                                                                                                                                                                                                                                                                                                                                                                                                                                                                                                                                                                                                                                                                                                                                                                                                                                                                                                                                                                                                                                                                                                                                                                                                                                                                                                                                                                                                                                                                                                                                                                                                                                                                                                                                                                                                                                                                                                                                                                                                                                                                                                                                                                                                                                                                                                                                                                                                                                                                                                                                                                                                                                                                                                                                                                                                                                                                                                                                                                                                                                                                                                                                                                                                                                                                                                                                                                                                                                                                                                                                                                                                                                                                                                                                                                                                                                                                                                                                                                                                                                                                                                                                                                                                                                                                                                                                                                                                                                                                                                                                                                                                                                                                                                                                                                                                                                                                                                                                                                                                                                                                                                                                                                                                                                                                                                                                                                                                                                                                                                                                                                                                                                                                                                                                                                                                                                                                                                                                                                                                                                                                                                                                                                                                                                                                                                                                                                                                                                                                                                                                                                                                                                                                                                                                                                                                                                                                                                                                                                                                                                                                                                                                                                                                                                                                                                                                                                                                                                                                                                                                                                                                                                                                                                                                                                                                                                                                                                                                                                                                                                                                                                                                                                                                                                                                                                                                                                                                                                                                                                                                                                                                                                                                                                                                                                                                                                                                                                                                                                                                                                                                                                                                                                                                                                                                                                                                                                                                                                                                                                                                                                                                                                                                                                                                                                                                                                                                                                                                                                                                                                                                                                                                                                                                                                                                                                                                                                                                                                                                                                                                                                                                                                                                                                                                                                                                                                                                                                                                                                                                                                                                                                                                                                                                                                                                                                                                                                                                                                                                                                                                                                                                                                                                                                                                                                                                                                                                                                                                                                                                                                                                                                                                                                                                                                                                                                                                                                                                                                                                                                                                                                                                                                                                                                                                                                                                                                                                                                                                                                                                                                                                                                                                                                                                                                                                                                                                                                                                                                                                                                                                                                                                                                                                                                                                                                                                                                                                                                                                                                                                                                                                                                                                                                                                                                                                                                                                                                                                                                                                                                                                                                                                                                                                                                                                                                                                                                                                                                                                                                                                                                                                                                                                                                                                                                                                                                                                                                                                                                                                                                                                                                                                                                                                                                                                                                                                                                                                                                                                                                                                                                                                                                                                                                                                                                                                                                                                                                                                                                                                                                                                                                                                                                                                                                                                                                                                                                                                                                                                                                                                                                                                                                                                                                                                                                                                                                                                                                                                                                                                                                                                                                                                                                                                                                                                                                                                                                                                                                                                                                                                                                                                                                                                                                                                                                                                                                                                                                                                                                                                                                                                                                                                                                                                                                                                                                                                                                                                                                                                                                                                                                                                                                                                                                                                                                                                                                                                                                                                                                                                                                                                                                                                                                                                                                                                                                                                                                                                                                                                                                                                                                                                                                                                                                                                                                                                                                                                                                                                                                                                                                                                                                                                                                                                                                                                                                                                                                                                                                                                                                                                                                                                                                                                                                                                                                                                                                                                                                                                                                                                                                                                                                                                                                                                                                                                                                                                                                                                                                                                                                                                                                                                                                                                                                                                                                                                                                                                                                                                                                                                                                                                                                                                                                                                                                                                                                                                                                                                                                                                                                                                                                                                                                                                                                                                                                                                                                                                                                                                                                                                                                                                                                                                                                                                                                                                                                                                                                                                                                                                                                                                                                                                                                                                                                                                                                                                                                                                                                                                                                                                                                                                                                                                                                                                                                                                                                                                                                                                                                                                                                                                                                                                                                                                                                                                                                                                                                                                                                                                                                                                                                                                                                                                                                                                                                                                                                                                                                                                                                                                                                                                                                                                                                                                                                                                                                                                                                                                                                                                                                                                                                                                                                                                                                                                                                                                                                                                                                                                                                                                                                                                                                                                                                                                                                                                                                                                                                                                                                                                                                                                                                                                                                                                                                                                                                                                                                                                                                                                                                                                                                                                                                                                                                                                                                                                                                                                                                                                                                                                                                                                                                                                                                                                                                                                                                                                                                                                                                                                                                                                                                                                                                                                                                                                                                                                                                                                                                                                                                                                                                                                                                                                                                                                                                                                                                                                                                                                                                                                                                                                                                                                                                                                                                                                                                                                                                                                                                                                                                                                                                                                                                                                                                                                                                                                                                                                                                                                                                                                                                                                                                                                                                                                                                                                                                                                                                                                                                                                                                                                                                                                                                                                                                                                                                                                                                                                                                                                                                                                                                                                                                                                                                                                                                                                                                                                                                                                                                                                                                                                                                                                                                                                                                                                                                                                                                                                                                                                                                                                                                                                                                                                                                                                                                                                                                                                                                                                                                                                                                                                                                                                                                                                                                                                                                                                                                                                                                                                                                                                                                                                                                                                                                                                                                                                                                                                                                                                                                                                                                                                                                                                                                                                                                                                                                                                                                                                                                                                                                                                                                                                                                                                                                                                                                                                                                                                                                                                                                                                                                                                                                                                                                                                                                                                                                                                                                                                                                                                                                                                                                                                                                                                                                                                                                                                                                                                                                                                                                                                                                                                                                                                                                                                                                                                                                                                                                                                                                                                                                                                                                                                                                                                                                                                                                                                                                                                                                                                                                                                                                                                                                                                                                                                                                                                                                                                                                                                                                                                                                                                                                                                                                                                                                                                                                                                                                                                                                                                                                                                                                                                                                                                                                                                                                                                                                                                                                                                                                                                                                                                                                                                                                                                                                                                                                                                                                                                                                                                                                                                                                                                                                                                                                                                                                                                                                                                                                                                                                                                                                                                                                                                                                                                                                                                                                                                                                                                                                                                                                                                                                                                                                                                                                                                                                                                                                                                                                                                                                                                                                                                                                                                                                                                                                                                                                                                                                                                                                                                                                                                                                                                                                                                                                                                                                                                                                                                                                                                                                                                                                                                                                                                                                                                                                                                                                                                                                                                                                                                                                                                                                                                                                                                                                                                                                                                                                                                                                                                                                                                                                                                                                                                                                                                                                                                                                                                                                                                                                                                                                                                                                                                                                                                                                                                                                                                                                                                                                                                                                                                                                                                                                                                                                                                                                                                                                                                                                                                                                                                                                                                                                                                                                                                                                                                                                                                                                                                                                                                                                                                                                                                                                                                                                                                                                                                                                                                                                                                                                                                                                                                                                                                                                                                                                                                                                                                                                                                                                                                                                                                                                                                                                                                                                                                                                                                                                                                                                                                                                                                                                                                                                                                                                                                                                                                                                                                                                                                                                                                                                                                                                                                                                
